odoo/addons/payroll/README.rst
odoo/addons/payroll/__init__.py
odoo/addons/payroll/__manifest__.py
odoo/addons/payroll/data/hr_payroll_data.xml
odoo/addons/payroll/data/hr_payroll_sequence.xml
odoo/addons/payroll/demo/hr_payroll_demo.xml
odoo/addons/payroll/i18n/af.po
odoo/addons/payroll/i18n/am.po
odoo/addons/payroll/i18n/ar.po
odoo/addons/payroll/i18n/az.po
odoo/addons/payroll/i18n/bg.po
odoo/addons/payroll/i18n/bn.po
odoo/addons/payroll/i18n/bs.po
odoo/addons/payroll/i18n/ca.po
odoo/addons/payroll/i18n/cs.po
odoo/addons/payroll/i18n/da.po
odoo/addons/payroll/i18n/de.po
odoo/addons/payroll/i18n/el.po
odoo/addons/payroll/i18n/en_GB.po
odoo/addons/payroll/i18n/es.po
odoo/addons/payroll/i18n/es_AR.po
odoo/addons/payroll/i18n/es_BO.po
odoo/addons/payroll/i18n/es_CL.po
odoo/addons/payroll/i18n/es_CO.po
odoo/addons/payroll/i18n/es_CR.po
odoo/addons/payroll/i18n/es_DO.po
odoo/addons/payroll/i18n/es_EC.po
odoo/addons/payroll/i18n/es_PE.po
odoo/addons/payroll/i18n/es_PY.po
odoo/addons/payroll/i18n/es_VE.po
odoo/addons/payroll/i18n/et.po
odoo/addons/payroll/i18n/eu.po
odoo/addons/payroll/i18n/fa.po
odoo/addons/payroll/i18n/fa_IR.po
odoo/addons/payroll/i18n/fi.po
odoo/addons/payroll/i18n/fil.po
odoo/addons/payroll/i18n/fo.po
odoo/addons/payroll/i18n/fr.po
odoo/addons/payroll/i18n/fr_BE.po
odoo/addons/payroll/i18n/fr_CA.po
odoo/addons/payroll/i18n/gl.po
odoo/addons/payroll/i18n/gu.po
odoo/addons/payroll/i18n/he.po
odoo/addons/payroll/i18n/hi.po
odoo/addons/payroll/i18n/hr.po
odoo/addons/payroll/i18n/hu.po
odoo/addons/payroll/i18n/id.po
odoo/addons/payroll/i18n/is.po
odoo/addons/payroll/i18n/it.po
odoo/addons/payroll/i18n/ja.po
odoo/addons/payroll/i18n/ka.po
odoo/addons/payroll/i18n/kab.po
odoo/addons/payroll/i18n/km.po
odoo/addons/payroll/i18n/ko.po
odoo/addons/payroll/i18n/lo.po
odoo/addons/payroll/i18n/lt.po
odoo/addons/payroll/i18n/lv.po
odoo/addons/payroll/i18n/mk.po
odoo/addons/payroll/i18n/mn.po
odoo/addons/payroll/i18n/nb.po
odoo/addons/payroll/i18n/ne.po
odoo_addon_payroll-18.0.1.2.1.dist-info/METADATA
odoo_addon_payroll-18.0.1.2.1.dist-info/WHEEL
odoo_addon_payroll-18.0.1.2.1.dist-info/top_level.txt
odoo_addon_payroll-18.0.1.2.1.dist-info/RECORD
