Metadata-Version: 2.1
Name: odoo-addon-payroll
Version: 18.0.1.2.1
Requires-Python: >=3.10
Requires-Dist: odoo==18.0.*
Summary: Manage your employee payroll records
Home-page: https://github.com/OCA/payroll
License: LGPL-3
Author: Odoo SA, Odoo Community Association (OCA)
Author-email: support@odoo-community.org
Classifier: Programming Language :: Python
Classifier: Framework :: Odoo
Classifier: Framework :: Odoo :: 18.0
Classifier: License :: OSI Approved :: GNU Lesser General Public License v3 (LGPLv3)
